{
	"configurations" : 
	[
		{
			"directories" : 
			[
				{
					"build" : ".",
					"jsonFile" : "directory-.-Debug-d0094a50bb2071803777.json",
					"projectIndex" : 0,
					"source" : "."
				}
			],
			"name" : "Debug",
			"projects" : 
			[
				{
					"directoryIndexes" : 
					[
						0
					],
					"name" : "Project"
				}
			],
			"targets" : []
		}
	],
	"kind" : "codemodel",
	"paths" : 
	{
		"build" : "C:/Users/Andreas Hummelmose/OneDrive/Skrivebord/Git/Automatic-bargain-hunting/build",
		"source" : "C:/Users/Andreas Hummelmose/OneDrive/Skrivebord/Git/Automatic-bargain-hunting"
	},
	"version" : 
	{
		"major" : 2,
		"minor" : 4
	}
}
